{"name":"Aditi Barbhai","tagline":"web developer, creator, information hunter-gatherer","body":"Hello! \r\n\r\nMy name is Aditi. I'm a Computer Science and Biotechnology student at the University of Toronto. I'm into web, mobile, and UI/UX.\r\n\r\n# Git Projects\r\n* [Catch The Monster!](https://github.com/aditibarbhai/catch-the-monster)\r\n* [Buxfer](https://github.com/aditibarbhai/buxfer)\r\n\r\nYou can find out more about me [here](http://aditi.barbhai.com), or see my other projects [here](https://aditi.barbhai.com/portfolio).","google":"","note":"Don't delete this file! It's used internally to help with page regeneration."}